autora/doc/__init__.py
autora/doc/_version.py
autora/doc/py.typed
autora/doc/util.py
autora/doc/classes/EvalResult.py
autora/doc/pipelines/main.py
autora/doc/pipelines/metrics.py
autora/doc/runtime/predict_hf.py
autora/doc/runtime/prompts.py
autora_doc-0.0.5.dist-info/METADATA
autora_doc-0.0.5.dist-info/WHEEL
autora_doc-0.0.5.dist-info/entry_points.txt
autora_doc-0.0.5.dist-info/licenses/LICENSE
autora_doc-0.0.5.dist-info/RECORD
