Metadata-Version: 2.1
Name: autora-doc
Version: 0.0.5
Summary: Automatic documentation generator from AutoRA code
Project-URL: Homepage, https://github.com/AutoResearch/autodoc
Author-email: Carlos Garcia Jurado Suarez <carlosg@uw.edu>
License: MIT License
License-File: LICENSE
Classifier: Development Status :: 4 - Beta
Classifier: Intended Audience :: Developers
Classifier: Intended Audience :: Science/Research
Classifier: License :: OSI Approved :: MIT License
Classifier: Operating System :: OS Independent
Classifier: Programming Language :: Python
Requires-Python: >=3.8
Requires-Dist: scipy
Requires-Dist: torch==2.0.1
Requires-Dist: transformers>=4.37.2
Requires-Dist: typer
Provides-Extra: azure
Requires-Dist: azureml-core; extra == 'azure'
Requires-Dist: azureml-mlflow; extra == 'azure'
Provides-Extra: cuda
Requires-Dist: accelerate>=0.24.1; extra == 'cuda'
Requires-Dist: bitsandbytes>=0.42.0; extra == 'cuda'
Requires-Dist: xformers; extra == 'cuda'
Provides-Extra: dev
Requires-Dist: black; extra == 'dev'
Requires-Dist: hf-transfer; extra == 'dev'
Requires-Dist: ipykernel; extra == 'dev'
Requires-Dist: ipython; extra == 'dev'
Requires-Dist: matplotlib; extra == 'dev'
Requires-Dist: mypy; extra == 'dev'
Requires-Dist: nbconvert; extra == 'dev'
Requires-Dist: nbsphinx; extra == 'dev'
Requires-Dist: pre-commit; extra == 'dev'
Requires-Dist: pytest; extra == 'dev'
Requires-Dist: pytest-cov; extra == 'dev'
Requires-Dist: sphinx; extra == 'dev'
Requires-Dist: sphinx-autoapi; extra == 'dev'
Requires-Dist: sphinx-rtd-theme; extra == 'dev'
Provides-Extra: pipelines
Requires-Dist: jsonlines; extra == 'pipelines'
Requires-Dist: mlflow; extra == 'pipelines'
Requires-Dist: nltk; extra == 'pipelines'
Requires-Dist: sentence-transformers>=2.3.1; extra == 'pipelines'
